{
  "dashboard": {
    "welcome": "Hola, 隆Bienvenido de nuevo! ",
    "totalRevenue": "Ingresos Totales",
    "newCustomers": "Nuevos Clientes",
    "activeAccounts": "Cuentas Activas",
    "growthRate": "Tasa de Crecimiento",
    "trendingUp": "Tendencia al alza este mes",
    "trendingDown": "Baj贸 un 20% este per铆odo",
    "visitorsLast6Months": "Visitantes de los 煤ltimos 6 meses",
    "acquisitionNeedsAttention": "La adquisici贸n necesita atenci贸n",
    "strongRetention": "Fuerte retenci贸n de usuarios",
    "engagementExceedsTargets": "El engagement supera los objetivos",
    "steadyPerformance": "Aumento constante del rendimiento",
    "meetsGrowthProjections": "Cumple las proyecciones de crecimiento"
  },
  "common": {
    "loading": "Cargando...",
    "error": "Error",
    "success": "xito"
  }
}

